monzo_viewer/__init__.py
monzo_viewer/app.py
monzo_viewer/cli.py
monzo_viewer/misc.py
monzo_viewer/templates/__init__.py
monzo_viewer/templates/error.html
monzo_viewer/templates/index.html
monzo_viewer/templates/raw_request.html
monzo_viewer/templates/setup.html
monzo_viewer/templates/success.html
monzo_viewer/templates/transactions.html
Monzo_Viewer-0.0.2.dist-info/LICENSE
Monzo_Viewer-0.0.2.dist-info/METADATA
Monzo_Viewer-0.0.2.dist-info/WHEEL
Monzo_Viewer-0.0.2.dist-info/entry_points.txt
Monzo_Viewer-0.0.2.dist-info/top_level.txt
Monzo_Viewer-0.0.2.dist-info/RECORD
